objetive/__init__.py
objetive-0.6.dist-info/LICENSE
objetive-0.6.dist-info/METADATA
objetive-0.6.dist-info/WHEEL
objetive-0.6.dist-info/top_level.txt
objetive-0.6.dist-info/RECORD
