Metadata-Version: 2.1
Name: objetive
Version: 0.6
Summary: A mini-crawler that aims to grab some text parts from some website or ip that responds http* 
Home-page: https://github.com/jul10l1r4/objetive
Author: Julio Lira
Author-email: jul10l1r4@disroot.org
License: UNKNOWN
Platform: UNKNOWN
Classifier: Programming Language :: Python :: 3
Classifier: License :: OSI Approved :: GNU General Public License v3 or later (GPLv3+)
Classifier: Operating System :: OS Independent
